dwlib/__init__.py
dwlib/datagenerator/__init__.py
dwlib/datagenerator/virtual_drift_generator.py
dwlib/myplot/MyPlot.py
dwlib/myplot/__init__.py
dwlib/myplot/test.py
dwlib/stats/__init__.py
dwlib/stats/binning.py
dwlib/stats/frechet_inception_distance.py
dwlib/stats/multivariate_sampling.py
dwlib/stats/piecewise_rejection_sampling.py
dwlib/stats/population_stability_index.py
dwlib/util/__init__.py
dwlib/util/colorprint.py
dwlib/util/function_list.py
dwlib/util/make_movie.py
dwlib/util/progressbar.py
dwlib-0.0.6.dist-info/METADATA
dwlib-0.0.6.dist-info/WHEEL
dwlib-0.0.6.dist-info/top_level.txt
dwlib-0.0.6.dist-info/RECORD
